{
  "_invariant": "INCIDENT: Neutrino USDN algorithmic-stable DEATH SPIRAL during the Terra/UST contagion. USDN's reflexive WAVES collateral decayed -> peg broke -> more WAVES minted/sold -> further decay. Ethereum-bridged USDN supply collapsed (redemption exit) 107.4M->81.4M (-24%) over the May-10->15 contagion week (real on-chain); price depegged hard. Mechanism (WAVES collateral ratio) is off-chain on Waves; the depeg + supply-exit symptom is Ethereum-readable.",
  "meta": {
    "token": "USDN",
    "chain": "ethereum",
    "chain_id": 1,
    "snapshot_ts": "2022-05-15T12:00:00Z",
    "snapshot_block": 14776687,
    "data_source": "on-chain Alchemy archive: USDN(Ethereum) totalSupply @ block 14776687"
  },
  "nodes": [
    {
      "node_id": "token:USDN",
      "type": "Token",
      "label": "Neutrino USD (Ethereum-bridged)",
      "address": "0x674C6Ad92Fd080e4004b2312b45f796a192D27a0",
      "chain": "ethereum",
      "chain_id": 1,
      "metadata": {
        "symbol": "USDN",
        "decimals": 18,
        "total_supply": 81445200000000000000000000,
        "supply_samples": [
          176288958000000000000000000,
          150000000000000000000000000,
          130000000000000000000000000,
          120000000000000000000000000,
          107369748000000000000000000,
          81445200000000000000000000
        ],
        "market_cap_usd": 65156160
      }
    },
    {
      "node_id": "protocol:curve",
      "type": "DefiProtocol",
      "label": "Curve",
      "address": "0x0000000000000000000000000000000000000ccc",
      "chain": "ethereum",
      "chain_id": 1,
      "metadata": {
        "architecture": "isolated_markets"
      }
    }
  ],
  "edges": [
    {
      "edge_id": "USDN-curve-pool",
      "source": "token:USDN",
      "target": "protocol:curve",
      "classification": {
        "edge_type": "collateral_isolated",
        "venue_type": "isolated_market",
        "protocol_class": "lending"
      },
      "core_weight": {
        "amount_token": 24433560,
        "amount_usd": 19546848,
        "pct_of_supply": 0.3,
        "pct_of_protocol_tvl": null
      },
      "oracle": {
        "oracle_type": "MARKET",
        "oracle_provider": "USDN/USD market",
        "oracle_address": null,
        "depeg_sensitive": true
      },
      "lending_risk": {
        "ltv": null,
        "lt": 0.85,
        "liquidation_bonus": null,
        "supply_cap": null,
        "borrow_cap": null,
        "reserve_factor": null,
        "utilization": 0.7,
        "is_frozen": false,
        "emode_category": null
      },
      "dex_metrics": null,
      "wrapper": null,
      "top_markets": [
        {
          "loan_asset": "USDC",
          "collateral_asset": "USDN",
          "lltv": 0.85,
          "market_size_usd": 19546848,
          "oracle_address": null,
          "utilization": 0.7
        }
      ]
    }
  ]
}